{"Type":1,"UniqueName":"#","Children":[{"Type":0,"UniqueName":"[Czas].[Kalendarzowy].[Rok].&[1990]","Children":[{"Type":0,"UniqueName":"[Czas].[Kalendarzowy].[Rok].&[1990].&[19901]","Children":[{"Type":1,"UniqueName":"[Czas].[Kalendarzowy].[Rok].&[1990].&[19901].&[199001]","Children":[]}]}]},{"Type":1,"UniqueName":"[Czas].[Kalendarzowy].[Rok].&[2005]","Children":[{"Type":0,"UniqueName":"[Czas].[Kalendarzowy].[Rok].&[2005].&[20051]","Children":[{"Type":1,"UniqueName":"[Czas].[Kalendarzowy].[Rok].&[2005].&[20051].&[200501]","Children":[]}]}]},{"Type":1,"UniqueName":"[Czas].[Kalendarzowy].[Rok].&[2006]","Children":[{"Type":0,"UniqueName":"[Czas].[Kalendarzowy].[Rok].&[2006].&[20061]","Children":[{"Type":1,"UniqueName":"[Czas].[Kalendarzowy].[Rok].&[2006].&[20061].&[200601]","Children":[]}]}]},{"Type":1,"UniqueName":"[Czas].[Kalendarzowy].[Rok].&[2007]","Children":[{"Type":0,"UniqueName":"[Czas].[Kalendarzowy].[Rok].&[2007].&[20071]","Children":[{"Type":1,"UniqueName":"[Czas].[Kalendarzowy].[Rok].&[2007].&[20071].&[200701]","Children":[]}]}]},{"Type":1,"UniqueName":"[Czas].[Kalendarzowy].[Rok].&[2008]","Children":[{"Type":0,"UniqueName":"[Czas].[Kalendarzowy].[Rok].&[2008].&[20081]","Children":[{"Type":1,"UniqueName":"[Czas].[Kalendarzowy].[Rok].&[2008].&[20081].&[200801]","Children":[]}]}]},{"Type":1,"UniqueName":"[Czas].[Kalendarzowy].[Rok].&[2009]","Children":[{"Type":0,"UniqueName":"[Czas].[Kalendarzowy].[Rok].&[2009].&[20091]","Children":[{"Type":1,"UniqueName":"[Czas].[Kalendarzowy].[Rok].&[2009].&[20091].&[200901]","Children":[]}]}]},{"Type":0,"UniqueName":"[Czas].[Kalendarzowy].[Rok].&[2010]","Children":[{"Type":0,"UniqueName":"[Czas].[Kalendarzowy].[Rok].&[2010].&[20101]","Children":[{"Type":1,"UniqueName":"[Czas].[Kalendarzowy].[Rok].&[2010].&[20101].&[201001]","Children":[]}]}]},{"Type":0,"UniqueName":"[Czas].[Kalendarzowy].[Rok].&[2011]","Children":[{"Type":0,"UniqueName":"[Czas].[Kalendarzowy].[Rok].&[2011].&[20111]","Children":[{"Type":1,"UniqueName":"[Czas].[Kalendarzowy].[Rok].&[2011].&[20111].&[201101]","Children":[]}]}]},{"Type":0,"UniqueName":"[Czas].[Kalendarzowy].[Rok].&[2012]","Children":[{"Type":0,"UniqueName":"[Czas].[Kalendarzowy].[Rok].&[2012].&[20121]","Children":[{"Type":1,"UniqueName":"[Czas].[Kalendarzowy].[Rok].&[2012].&[20121].&[201201]","Children":[]}]}]},{"Type":0,"UniqueName":"[Czas].[Kalendarzowy].[Rok].&[2013]","Children":[{"Type":0,"UniqueName":"[Czas].[Kalendarzowy].[Rok].&[2013].&[20131]","Children":[{"Type":1,"UniqueName":"[Czas].[Kalendarzowy].[Rok].&[2013].&[20131].&[201301]","Children":[]}]}]},{"Type":0,"UniqueName":"[Czas].[Kalendarzowy].[Rok].&[2014]","Children":[{"Type":0,"UniqueName":"[Czas].[Kalendarzowy].[Rok].&[2014].&[20141]","Children":[{"Type":1,"UniqueName":"[Czas].[Kalendarzowy].[Rok].&[2014].&[20141].&[201401]","Children":[]}]}]},{"Type":0,"UniqueName":"[Czas].[Kalendarzowy].[Rok].&[2015]","Children":[{"Type":0,"UniqueName":"[Czas].[Kalendarzowy].[Rok].&[2015].&[20151]","Children":[{"Type":1,"UniqueName":"[Czas].[Kalendarzowy].[Rok].&[2015].&[20151].&[201501]","Children":[]}]}]},{"Type":0,"UniqueName":"[Czas].[Kalendarzowy].[Rok].&[2016]","Children":[{"Type":0,"UniqueName":"[Czas].[Kalendarzowy].[Rok].&[2016].&[20161]","Children":[{"Type":1,"UniqueName":"[Czas].[Kalendarzowy].[Rok].&[2016].&[20161].&[201601]","Children":[]}]}]},{"Type":0,"UniqueName":"[Czas].[Kalendarzowy].[Rok].&[2017]","Children":[{"Type":0,"UniqueName":"[Czas].[Kalendarzowy].[Rok].&[2017].&[20171]","Children":[{"Type":1,"UniqueName":"[Czas].[Kalendarzowy].[Rok].&[2017].&[20171].&[201701]","Children":[]}]}]},{"Type":0,"UniqueName":"[Czas].[Kalendarzowy].[Rok].&[2018]","Children":[{"Type":0,"UniqueName":"[Czas].[Kalendarzowy].[Rok].&[2018].&[20181]","Children":[{"Type":1,"UniqueName":"[Czas].[Kalendarzowy].[Rok].&[2018].&[20181].&[201801]","Children":[]}]}]},{"Type":0,"UniqueName":"[Czas].[Kalendarzowy].[Rok].&[2019]","Children":[{"Type":0,"UniqueName":"[Czas].[Kalendarzowy].[Rok].&[2019].&[20191]","Children":[{"Type":1,"UniqueName":"[Czas].[Kalendarzowy].[Rok].&[2019].&[20191].&[201901]","Children":[]}]}]},{"Type":1,"UniqueName":"[Czas].[Kalendarzowy].[Rok].&[2020]","Children":[{"Type":0,"UniqueName":"[Czas].[Kalendarzowy].[Rok].&[2020].&[20201]","Children":[{"Type":1,"UniqueName":"[Czas].[Kalendarzowy].[Rok].&[2020].&[20201].&[202001]","Children":[]}]}]},{"Type":1,"UniqueName":"[Czas].[Kalendarzowy].[Rok].&[2227]","Children":[{"Type":0,"UniqueName":"[Czas].[Kalendarzowy].[Rok].&[2227].&[22271]","Children":[{"Type":1,"UniqueName":"[Czas].[Kalendarzowy].[Rok].&[2227].&[22271].&[222701]","Children":[]}]}]},{"Type":0,"UniqueName":"[Czas].[Kalendarzowy].[Rok].&[1989]","Children":[{"Type":0,"UniqueName":"[Czas].[Kalendarzowy].[Rok].&[1989].&[19891]","Children":[{"Type":1,"UniqueName":"[Czas].[Kalendarzowy].[Rok].&[1989].&[19891].&[198901]","Children":[]}]}]}]}